apeeper/__init__.py
apeeper/extras.py
apeeper/register.py
apeeper/run.py
apeeper-0.3.data/scripts/apeeper_gunicorn_conf.py
apeeper-0.3.data/scripts/apeeperd
apeeper-0.3.dist-info/LICENSE
apeeper-0.3.dist-info/METADATA
apeeper-0.3.dist-info/WHEEL
apeeper-0.3.dist-info/top_level.txt
apeeper-0.3.dist-info/RECORD
