Metadata-Version: 2.1
Name: apeeper
Version: 0.3
Summary: EC2 meta data service
Home-page: UNKNOWN
Author: Thinkst Applied Research
Author-email: apeeper@thinkst.com
License: GNU GPLv3
Platform: any
Classifier: Programming Language :: Python :: 2
Requires-Dist: python-iptables (==0.13.0)
Requires-Dist: gunicorn (==19.9.0)
Requires-Dist: Flask (==1.0.2)
Requires-Dist: requests (==2.20.0)
Requires-Dist: setproctitle (==1.1.10)
